add_pyproject/__about__.py
add_pyproject/__init__.py
add_pyproject/__main__.py
add_pyproject-0.1.0.dist-info/METADATA
add_pyproject-0.1.0.dist-info/WHEEL
add_pyproject-0.1.0.dist-info/licenses/LICENSE.txt
add_pyproject-0.1.0.dist-info/RECORD
